{
    "title": [
        "Apple MacBook Air 13\" 3.2GHz i7 Turbo - BIG SUR - 8GB RAM 512GB SSD - WARRANTY"
    ],
    "current_price": [
        "US $299.00"
    ],
    "original_price": [
        "US $598.00"
    ],
    "savings": [
        "(50% off)"
    ],
    "image_links": [
        [
            "https://i.ebayimg.com/images/g/SsUAAOSwK29miFon/s-l140.jpg",
            "https://i.ebayimg.com/images/g/QesAAOSwmExmiFop/s-l140.jpg",
            "https://i.ebayimg.com/images/g/vDEAAOSwArVmiFop/s-l140.png",
            "https://i.ebayimg.com/images/g/aW4AAOSwqT9miFop/s-l140.jpg",
            "https://i.ebayimg.com/images/g/RiUAAOSwLtxmiFop/s-l140.jpg",
            "https://i.ebayimg.com/images/g/OlwAAOSweRlmiFon/s-l140.jpg"
        ]
    ],
    "product_url": [
        "https://www.ebay.com/itm/404925427501"
    ],
    "seller": [
        "ROSCOE"
    ],
    "seller_feedback": "99.4% positive",
    "shipping": "US $40.62"
}